nmt/__init__.py
nmt/inference.py
nmt/main.py
nmt/main_script.py
nmt/toy_problem.py
nmt/training.py
nmt/models/helpers.py
nmt/models/seq2seq.py
nmt/models/modules/__init__.py
nmt/models/modules/decoder.py
nmt/models/modules/encoder.py
nmt/utils/__init__.py
nmt/utils/data_generator.py
nmt/utils/load_pretrained_model.py
nmt/utils/load_raw_data.py
nmt/utils/postprocess.py
nmt/utils/preprocess.py
nmt/utils/spacy_language_model.py
nmt/utils/token_intersection.py
nmt-0.0.6.dist-info/METADATA
nmt-0.0.6.dist-info/WHEEL
nmt-0.0.6.dist-info/entry_points.txt
nmt-0.0.6.dist-info/top_level.txt
nmt-0.0.6.dist-info/RECORD
